vema/__init__.py
vema/__main__.py
vema/src/cli.py
vema/src/page.py
vema/src/vema.py
vema/src/exceptions/wrongExtension.py
vema/src/exceptions/wrongPath.py
vema-0.1.4.dist-info/LICENSE
vema-0.1.4.dist-info/METADATA
vema-0.1.4.dist-info/WHEEL
vema-0.1.4.dist-info/top_level.txt
vema-0.1.4.dist-info/RECORD
