Metadata-Version: 2.1
Name: vema
Version: 0.1.4
Summary: Vema is a solution for developing static web pages, from Python + Flask, which has the basic tools and already configured to focus on the design of the pages.
Home-page: https://github.com/episuarez/vema
Author: Epifanio Suárez Martínez
Author-email: episuarez@pm.es
License: BSD
Platform: any
Classifier: License :: OSI Approved :: BSD License
Classifier: Operating System :: OS Independent
Classifier: Programming Language :: Python :: Implementation :: PyPy
Classifier: Development Status :: 2 - Pre-Alpha
Classifier: Programming Language :: Python :: 3.6
Classifier: Programming Language :: Python :: 3.7
Classifier: Programming Language :: Python :: 3.8
Classifier: Programming Language :: Python :: 3.9
Classifier: Programming Language :: Python :: 3.10
License-File: LICENSE
Requires-Dist: Flask
Requires-Dist: Frozen-Flask
Requires-Dist: argparse
